{
  "type": "object",
  "title": "Credentials",
  "format": "table",
  "$schema": "http://json-schema.org/draft-04/schema#",
  "required": [
    "#secret",
    "#api_key"
  ],
  "properties": {
    "#api_key": {
      "type": "string",
      "title": "API Key",
      "format": "password",
      "description": "Sailthru API Key",
      "propertyOrder": 33
    },
    "#secret": {
      "type": "string",
      "title": "Sailthru Secret",
      "format": "password",
      "description": "Sailthru Secret",
      "propertyOrder": 36
    },
    "test_connection": {
      "type": "button",
      "format": "test-connection",
      "propertyOrder": 60
    }
  }
}